CHANGELOG.md
sock_websocket.py
sock_websocket-0.6.0.dist-info/WHEEL
sock_websocket-0.6.0.dist-info/METADATA
sock_websocket-0.6.0.dist-info/RECORD
