Metadata-Version: 2.1
Name: sock-websocket
Version: 0.6.0
Summary: Small script to simplify network communication
License: MIT
Keywords: socket,telnet,network
Author: hellman
Requires-Python: >=3.4,<4.0
Classifier: Intended Audience :: Developers
Classifier: License :: OSI Approved :: MIT License
Classifier: Operating System :: Unix
Classifier: Programming Language :: Python :: 3
Classifier: Programming Language :: Python :: 3.4
Classifier: Programming Language :: Python :: 3.5
Classifier: Programming Language :: Python :: 3.6
Classifier: Programming Language :: Python :: 3.7
Classifier: Programming Language :: Python :: 3.8
Classifier: Programming Language :: Python :: 3.9
Classifier: Topic :: System :: Networking
Requires-Dist: websocket_client (>=0.57.0,<0.58.0)
Project-URL: homepage, http://github.com/bongtrop/sock/tree/websocket
